{
  "collectionName": "components_party_convention_dai_hois",
  "info": {
    "displayName": "Đại hội"
  },
  "options": {},
  "attributes": {
    "anh_dai_hoi": {
      "type": "media",
      "multiple": false,
      "allowedTypes": [
        "images",
        "files",
        "videos",
        "audios"
      ]
    },
    "anh_chi_tiet": {
      "type": "media",
      "multiple": false,
      "allowedTypes": [
        "images",
        "files",
        "videos",
        "audios"
      ]
    },
    "mo_ta": {
      "type": "customField",
      "customField": "plugin::ckeditor5.CKEditor",
      "options": {
        "preset": "defaultHtml"
      }
    },
    "thong_tin_chi_tiet": {
      "type": "media",
      "multiple": false,
      "allowedTypes": [
        "images",
        "files",
        "videos",
        "audios"
      ]
    },
    "link": {
      "type": "string"
    }
  },
  "config": {}
}
